README.md
setup.py
imikrokosmos.egg-info/PKG-INFO
imikrokosmos.egg-info/SOURCES.txt
imikrokosmos.egg-info/dependency_links.txt
imikrokosmos.egg-info/top_level.txt
mikrokosmoskernel/__init__.py
mikrokosmoskernel/__main__.py
mikrokosmoskernel/kernel.js
mikrokosmoskernel/kernel.json
mikrokosmoskernel/mikrokosmoskernel.py