Metadata-Version: 1.0
Name: imikrokosmos
Version: 0.1.8
Summary: A Jupyter kernel for the mikrokosmos lambda interpreter
Home-page: https://github.com/mroman42/jupyter-mikrokosmos
Author: Mario Román
Author-email: mromang08@gmail.com
License: GPLv3
Platform: UNKNOWN
